fetcharoo/__init__.py
fetcharoo/cli.py
fetcharoo/downloader.py
fetcharoo/fetcharoo.py
fetcharoo/file_utils.py
fetcharoo/filtering.py
fetcharoo/pdf_utils.py
fetcharoo/py.typed
fetcharoo-0.2.0.dist-info/METADATA
fetcharoo-0.2.0.dist-info/WHEEL
fetcharoo-0.2.0.dist-info/entry_points.txt
fetcharoo-0.2.0.dist-info/RECORD
