Metadata-Version: 2.4
Name: fetcharoo
Version: 0.2.0
Summary: A Python library for downloading PDF files from webpages, with support for recursive link following and PDF merging.
License: MIT
Keywords: pdf,download,scraper,web,merge
Author: Mark A. Lifson, Ph.D.
Author-email: mlifson@gmail.com
Requires-Python: >=3.10,<4.0
Classifier: Development Status :: 4 - Beta
Classifier: Intended Audience :: Developers
Classifier: License :: OSI Approved :: MIT License
Classifier: Operating System :: OS Independent
Classifier: Programming Language :: Python :: 3
Classifier: Programming Language :: Python :: 3.10
Classifier: Programming Language :: Python :: 3.11
Classifier: Programming Language :: Python :: 3.12
Classifier: Programming Language :: Python :: 3.13
Classifier: Programming Language :: Python :: 3.14
Classifier: Topic :: Internet :: WWW/HTTP
Classifier: Topic :: Software Development :: Libraries :: Python Modules
Requires-Dist: beautifulsoup4 (>=4.12.3,<5.0.0)
Requires-Dist: pymupdf (>=1.25.0,<2.0.0)
Requires-Dist: requests (>=2.32.3,<3.0.0)
Requires-Dist: tqdm (>=4.66,<5.0)
Project-URL: Repository, https://github.com/MALathon/fetcharoo
